fastchat/__init__.py
fastchat/api/__init__.py
fastchat/api/api.py
fastchat/api/settings.py
fastchat/api/routes/chat.py
fastchat/app/chat/chat.py
fastchat/app/chat/message.py
fastchat/app/chat/features/llm_provider.py
fastchat/app/chat/features/step.py
fastchat/app/client_db/client_db.py
fastchat/app/mcp_manager/client.py
fastchat/app/mcp_manager/servers.py
fastchat/app/mcp_manager/services/__init__.py
fastchat/app/mcp_manager/services/service.py
fastchat/app/mcp_manager/services/prompt/prompt.py
fastchat/app/mcp_manager/services/resource/resource.py
fastchat/app/mcp_manager/services/resource/utils.py
fastchat/app/mcp_manager/services/tool/tool.py
fastchat/app/mcp_manager/sessions/httpstrem.py
fastchat/app/mcp_manager/sessions/stdio.py
fastchat/app/services/llm/__init__.py
fastchat/app/services/llm/llm.py
fastchat/app/services/llm/models/openai_service/gpt.py
fastchat/app/services/llm/prompts/system_prompts.py
fastchat/app/services/llm/prompts/user_prompts.py
fastchat/app/services/llm/prompts/texts/system_prompts.yaml
fastchat/app/services/llm/prompts/texts/system_prompts_es.yaml
fastchat/config/__init__.py
fastchat/config/auth_api.py
fastchat/config/llm_config.py
fastchat/config/logger.py
fastchat/local/local_chat.py
fastchat/utils/clear_console.py
fastchat/utils/get_running_loop.py
fastchat/utils/print_terminal.py
fastchat/utils/stdio_session_params.py
fastchat_mcp-1.2.8.dist-info/licenses/LICENSE
fastchat_mcp-1.2.8.dist-info/METADATA
fastchat_mcp-1.2.8.dist-info/WHEEL
fastchat_mcp-1.2.8.dist-info/top_level.txt
fastchat_mcp-1.2.8.dist-info/RECORD
