Metadata-Version: 2.4
Name: fastchat-mcp
Version: 1.2.8
Summary: Python client, based on fastmcp, for connecting to MCP servers through multiple protocols, specifically designed to work with integrated language models.
Author-email: Raúl Beltrán Gómez <rb58853@gmail.com>
License-Expression: MIT
Project-URL: Homepage, https://github.com/rb58853/fastchat-mcp
Project-URL: Issues, https://github.com/rb58853/fastchat-mcp/issues
Classifier: Programming Language :: Python :: 3
Classifier: Operating System :: OS Independent
Requires-Python: >=3.11
License-File: LICENSE
Requires-Dist: openai>=1.68.2
Requires-Dist: mcp[cli]==1.22.0
Requires-Dist: fastauth-api>=0.0.5
Requires-Dist: mcp-oauth>=0.0.6
Requires-Dist: fastapi
Requires-Dist: websockets
Requires-Dist: requests
Requires-Dist: PyYAML
Requires-Dist: aiohttp
Dynamic: license-file
